servicenow_api_client/__init__.py
servicenow_api_client/exceptions.py
servicenow_api_client/service_now_client.py
servicenow_api_client-0.1.2.dist-info/LICENSE
servicenow_api_client-0.1.2.dist-info/METADATA
servicenow_api_client-0.1.2.dist-info/WHEEL
servicenow_api_client-0.1.2.dist-info/top_level.txt
servicenow_api_client-0.1.2.dist-info/RECORD
